whichcraft.py
whichcraft-0.6.0.dist-info/AUTHORS.rst
whichcraft-0.6.0.dist-info/LICENSE
whichcraft-0.6.0.dist-info/METADATA
whichcraft-0.6.0.dist-info/WHEEL
whichcraft-0.6.0.dist-info/top_level.txt
whichcraft-0.6.0.dist-info/RECORD
