Metadata-Version: 1.1
Name: whichcraft
Version: 0.6.0
Summary: This package provides cross-platform cross-python shutil.which functionality.
Home-page: https://github.com/pydanny/whichcraft
Author: Daniel Roy Greenfeld
Author-email: pydanny@gmail.com
License: BSD
Keywords: whichcraft
Platform: UNKNOWN
Classifier: Development Status :: 5 - Production/Stable
Classifier: Intended Audience :: Developers
Classifier: License :: OSI Approved :: BSD License
Classifier: Natural Language :: English
Classifier: Programming Language :: Python :: 2
Classifier: Programming Language :: Python :: 2.7
Classifier: Programming Language :: Python :: 3
Classifier: Programming Language :: Python :: 3.6
Classifier: Programming Language :: Python :: 3.7
